{
    "version": "4.5.5",
    "flags": {},
    "shapes": [
        {
            "label": "car",
            "line_color": null,
            "fill_color": null,
            "points": [
                [
                    392.0,
                    243.0
                ],
                [
                    403.0,
                    243.0
                ],
                [
                    403.0,
                    267.0
                ],
                [
                    392.0,
                    267.0
                ]
            ],
            "shape_type": "polygon",
            "flags": {},
            "area": -1,
            "bbox": [
                392.0,
                243.0,
                11.0,
                24.0
            ],
            "segmentation": [
                [
                    392.0,
                    243.0,
                    403.0,
                    243.0,
                    403.0,
                    267.0,
                    392.0,
                    267.0
                ]
            ]
        },
        {
            "label": "car",
            "line_color": null,
            "fill_color": null,
            "points": [
                [
                    406.0,
                    236.0
                ],
                [
                    416.0,
                    236.0
                ],
                [
                    416.0,
                    256.0
                ],
                [
                    406.0,
                    256.0
                ]
            ],
            "shape_type": "polygon",
            "flags": {},
            "area": -1,
            "bbox": [
                406.0,
                236.0,
                10.0,
                20.0
            ],
            "segmentation": [
                [
                    406.0,
                    236.0,
                    416.0,
                    236.0,
                    416.0,
                    256.0,
                    406.0,
                    256.0
                ]
            ]
        },
        {
            "label": "car",
            "line_color": null,
            "fill_color": null,
            "points": [
                [
                    431.0,
                    244.0
                ],
                [
                    453.0,
                    244.0
                ],
                [
                    453.0,
                    255.0
                ],
                [
                    431.0,
                    255.0
                ]
            ],
            "shape_type": "polygon",
            "flags": {},
            "area": -1,
            "bbox": [
                431.0,
                244.0,
                22.0,
                11.0
            ],
            "segmentation": [
                [
                    431.0,
                    244.0,
                    453.0,
                    244.0,
                    453.0,
                    255.0,
                    431.0,
                    255.0
                ]
            ]
        },
        {
            "label": "car",
            "line_color": null,
            "fill_color": null,
            "points": [
                [
                    130.0,
                    322.0
                ],
                [
                    154.0,
                    322.0
                ],
                [
                    154.0,
                    332.0
                ],
                [
                    130.0,
                    332.0
                ]
            ],
            "shape_type": "polygon",
            "flags": {},
            "area": -1,
            "bbox": [
                130.0,
                322.0,
                24.0,
                10.0
            ],
            "segmentation": [
                [
                    130.0,
                    322.0,
                    154.0,
                    322.0,
                    154.0,
                    332.0,
                    130.0,
                    332.0
                ]
            ]
        }
    ],
    "lineColor": [
        0,
        255,
        0,
        128
    ],
    "fillColor": [
        255,
        0,
        0,
        128
    ],
    "imagePath": "F:\\2021\\3\u2014\u2014\u7b97\u6cd5\u7814\u7a76\\\u8f66\u8f86\u68c0\u6d4b\\1\u2014\u963f\u5e03\u624e\u6bd4\u8f66\u8f86\\labelme\\img\\GOOGLE_mosaic_clip_512_2814.png",
    "imageData": "",
    "imageHeight": 512,
    "imageWidth": 512
}