{
    "version": "4.5.5",
    "flags": {},
    "shapes": [
        {
            "label": "car",
            "line_color": null,
            "fill_color": null,
            "points": [
                [
                    215.0,
                    320.0
                ],
                [
                    236.0,
                    320.0
                ],
                [
                    236.0,
                    329.0
                ],
                [
                    215.0,
                    329.0
                ]
            ],
            "shape_type": "polygon",
            "flags": {},
            "area": -1,
            "bbox": [
                215.0,
                320.0,
                21.0,
                9.0
            ],
            "segmentation": [
                [
                    215.0,
                    320.0,
                    236.0,
                    320.0,
                    236.0,
                    329.0,
                    215.0,
                    329.0
                ]
            ]
        },
        {
            "label": "car",
            "line_color": null,
            "fill_color": null,
            "points": [
                [
                    219.0,
                    387.0
                ],
                [
                    238.0,
                    387.0
                ],
                [
                    238.0,
                    398.0
                ],
                [
                    219.0,
                    398.0
                ]
            ],
            "shape_type": "polygon",
            "flags": {},
            "area": -1,
            "bbox": [
                219.0,
                387.0,
                19.0,
                11.0
            ],
            "segmentation": [
                [
                    219.0,
                    387.0,
                    238.0,
                    387.0,
                    238.0,
                    398.0,
                    219.0,
                    398.0
                ]
            ]
        },
        {
            "label": "car",
            "line_color": null,
            "fill_color": null,
            "points": [
                [
                    222.0,
                    413.0
                ],
                [
                    240.0,
                    413.0
                ],
                [
                    240.0,
                    424.0
                ],
                [
                    222.0,
                    424.0
                ]
            ],
            "shape_type": "polygon",
            "flags": {},
            "area": -1,
            "bbox": [
                222.0,
                413.0,
                18.0,
                11.0
            ],
            "segmentation": [
                [
                    222.0,
                    413.0,
                    240.0,
                    413.0,
                    240.0,
                    424.0,
                    222.0,
                    424.0
                ]
            ]
        },
        {
            "label": "car",
            "line_color": null,
            "fill_color": null,
            "points": [
                [
                    188.0,
                    300.0
                ],
                [
                    188.0,
                    286.0
                ],
                [
                    199.0,
                    286.0
                ],
                [
                    199.0,
                    300.0
                ]
            ],
            "shape_type": "polygon",
            "flags": {},
            "area": -1,
            "bbox": [
                188.0,
                286.0,
                11.0,
                14.0
            ],
            "segmentation": [
                [
                    188.0,
                    300.0,
                    188.0,
                    286.0,
                    199.0,
                    286.0,
                    199.0,
                    300.0
                ]
            ]
        },
        {
            "label": "car",
            "line_color": null,
            "fill_color": null,
            "points": [
                [
                    191.0,
                    321.0
                ],
                [
                    191.0,
                    306.0
                ],
                [
                    209.0,
                    306.0
                ],
                [
                    209.0,
                    321.0
                ]
            ],
            "shape_type": "polygon",
            "flags": {},
            "area": -1,
            "bbox": [
                191.0,
                306.0,
                18.0,
                15.0
            ],
            "segmentation": [
                [
                    191.0,
                    321.0,
                    191.0,
                    306.0,
                    209.0,
                    306.0,
                    209.0,
                    321.0
                ]
            ]
        },
        {
            "label": "car",
            "line_color": null,
            "fill_color": null,
            "points": [
                [
                    197.0,
                    334.0
                ],
                [
                    197.0,
                    318.0
                ],
                [
                    211.0,
                    318.0
                ],
                [
                    211.0,
                    334.0
                ]
            ],
            "shape_type": "polygon",
            "flags": {},
            "area": -1,
            "bbox": [
                197.0,
                318.0,
                14.0,
                16.0
            ],
            "segmentation": [
                [
                    197.0,
                    334.0,
                    197.0,
                    318.0,
                    211.0,
                    318.0,
                    211.0,
                    334.0
                ]
            ]
        },
        {
            "label": "car",
            "line_color": null,
            "fill_color": null,
            "points": [
                [
                    194.0,
                    376.0
                ],
                [
                    212.0,
                    376.0
                ],
                [
                    212.0,
                    390.0
                ],
                [
                    194.0,
                    390.0
                ]
            ],
            "shape_type": "polygon",
            "flags": {},
            "area": -1,
            "bbox": [
                194.0,
                376.0,
                18.0,
                14.0
            ],
            "segmentation": [
                [
                    194.0,
                    376.0,
                    212.0,
                    376.0,
                    212.0,
                    390.0,
                    194.0,
                    390.0
                ]
            ]
        },
        {
            "label": "car",
            "line_color": null,
            "fill_color": null,
            "points": [
                [
                    79.0,
                    237.0
                ],
                [
                    98.0,
                    237.0
                ],
                [
                    98.0,
                    245.0
                ],
                [
                    79.0,
                    245.0
                ]
            ],
            "shape_type": "polygon",
            "flags": {},
            "area": -1,
            "bbox": [
                79.0,
                237.0,
                19.0,
                8.0
            ],
            "segmentation": [
                [
                    79.0,
                    237.0,
                    98.0,
                    237.0,
                    98.0,
                    245.0,
                    79.0,
                    245.0
                ]
            ]
        },
        {
            "label": "car",
            "line_color": null,
            "fill_color": null,
            "points": [
                [
                    129.0,
                    255.0
                ],
                [
                    137.0,
                    255.0
                ],
                [
                    137.0,
                    272.0
                ],
                [
                    129.0,
                    272.0
                ]
            ],
            "shape_type": "polygon",
            "flags": {},
            "area": -1,
            "bbox": [
                129.0,
                255.0,
                8.0,
                17.0
            ],
            "segmentation": [
                [
                    129.0,
                    255.0,
                    137.0,
                    255.0,
                    137.0,
                    272.0,
                    129.0,
                    272.0
                ]
            ]
        },
        {
            "label": "car",
            "line_color": null,
            "fill_color": null,
            "points": [
                [
                    136.0,
                    182.0
                ],
                [
                    154.0,
                    182.0
                ],
                [
                    154.0,
                    192.0
                ],
                [
                    136.0,
                    192.0
                ]
            ],
            "shape_type": "polygon",
            "flags": {},
            "area": -1,
            "bbox": [
                136.0,
                182.0,
                18.0,
                10.0
            ],
            "segmentation": [
                [
                    136.0,
                    182.0,
                    154.0,
                    182.0,
                    154.0,
                    192.0,
                    136.0,
                    192.0
                ]
            ]
        },
        {
            "label": "car",
            "line_color": null,
            "fill_color": null,
            "points": [
                [
                    109.0,
                    156.0
                ],
                [
                    127.0,
                    156.0
                ],
                [
                    127.0,
                    165.0
                ],
                [
                    109.0,
                    165.0
                ]
            ],
            "shape_type": "polygon",
            "flags": {},
            "area": -1,
            "bbox": [
                109.0,
                156.0,
                18.0,
                9.0
            ],
            "segmentation": [
                [
                    109.0,
                    156.0,
                    127.0,
                    156.0,
                    127.0,
                    165.0,
                    109.0,
                    165.0
                ]
            ]
        },
        {
            "label": "car",
            "line_color": null,
            "fill_color": null,
            "points": [
                [
                    417.0,
                    280.0
                ],
                [
                    437.0,
                    280.0
                ],
                [
                    437.0,
                    292.0
                ],
                [
                    417.0,
                    292.0
                ]
            ],
            "shape_type": "polygon",
            "flags": {},
            "area": -1,
            "bbox": [
                417.0,
                280.0,
                20.0,
                12.0
            ],
            "segmentation": [
                [
                    417.0,
                    280.0,
                    437.0,
                    280.0,
                    437.0,
                    292.0,
                    417.0,
                    292.0
                ]
            ]
        }
    ],
    "lineColor": [
        0,
        255,
        0,
        128
    ],
    "fillColor": [
        255,
        0,
        0,
        128
    ],
    "imagePath": "F:\\2021\\3\u2014\u2014\u7b97\u6cd5\u7814\u7a76\\\u8f66\u8f86\u68c0\u6d4b\\1\u2014\u963f\u5e03\u624e\u6bd4\u8f66\u8f86\\labelme\\img\\GOOGLE_mosaic_clip_512_2063.png",
    "imageData": "",
    "imageHeight": 512,
    "imageWidth": 512
}