{
    "version": "4.5.5",
    "flags": {},
    "shapes": [
        {
            "label": "car",
            "line_color": null,
            "fill_color": null,
            "points": [
                [
                    139.0,
                    314.0
                ],
                [
                    151.0,
                    314.0
                ],
                [
                    151.0,
                    337.0
                ],
                [
                    139.0,
                    337.0
                ]
            ],
            "shape_type": "polygon",
            "flags": {},
            "area": -1,
            "bbox": [
                139.0,
                314.0,
                12.0,
                23.0
            ],
            "segmentation": [
                [
                    139.0,
                    314.0,
                    151.0,
                    314.0,
                    151.0,
                    337.0,
                    139.0,
                    337.0
                ]
            ]
        },
        {
            "label": "car",
            "line_color": null,
            "fill_color": null,
            "points": [
                [
                    199.0,
                    261.0
                ],
                [
                    209.0,
                    261.0
                ],
                [
                    209.0,
                    283.0
                ],
                [
                    199.0,
                    283.0
                ]
            ],
            "shape_type": "polygon",
            "flags": {},
            "area": -1,
            "bbox": [
                199.0,
                261.0,
                10.0,
                22.0
            ],
            "segmentation": [
                [
                    199.0,
                    261.0,
                    209.0,
                    261.0,
                    209.0,
                    283.0,
                    199.0,
                    283.0
                ]
            ]
        },
        {
            "label": "car",
            "line_color": null,
            "fill_color": null,
            "points": [
                [
                    131.0,
                    110.0
                ],
                [
                    141.0,
                    110.0
                ],
                [
                    141.0,
                    128.0
                ],
                [
                    131.0,
                    128.0
                ]
            ],
            "shape_type": "polygon",
            "flags": {},
            "area": -1,
            "bbox": [
                131.0,
                110.0,
                10.0,
                18.0
            ],
            "segmentation": [
                [
                    131.0,
                    110.0,
                    141.0,
                    110.0,
                    141.0,
                    128.0,
                    131.0,
                    128.0
                ]
            ]
        },
        {
            "label": "car",
            "line_color": null,
            "fill_color": null,
            "points": [
                [
                    115.0,
                    64.0
                ],
                [
                    125.0,
                    64.0
                ],
                [
                    125.0,
                    87.0
                ],
                [
                    115.0,
                    87.0
                ]
            ],
            "shape_type": "polygon",
            "flags": {},
            "area": -1,
            "bbox": [
                115.0,
                64.0,
                10.0,
                23.0
            ],
            "segmentation": [
                [
                    115.0,
                    64.0,
                    125.0,
                    64.0,
                    125.0,
                    87.0,
                    115.0,
                    87.0
                ]
            ]
        },
        {
            "label": "car",
            "line_color": null,
            "fill_color": null,
            "points": [
                [
                    193.0,
                    205.0
                ],
                [
                    209.0,
                    205.0
                ],
                [
                    209.0,
                    238.0
                ],
                [
                    193.0,
                    238.0
                ]
            ],
            "shape_type": "polygon",
            "flags": {},
            "area": -1,
            "bbox": [
                193.0,
                205.0,
                16.0,
                33.0
            ],
            "segmentation": [
                [
                    193.0,
                    205.0,
                    209.0,
                    205.0,
                    209.0,
                    238.0,
                    193.0,
                    238.0
                ]
            ]
        },
        {
            "label": "car",
            "line_color": null,
            "fill_color": null,
            "points": [
                [
                    192.0,
                    96.0
                ],
                [
                    201.0,
                    96.0
                ],
                [
                    201.0,
                    113.0
                ],
                [
                    192.0,
                    113.0
                ]
            ],
            "shape_type": "polygon",
            "flags": {},
            "area": -1,
            "bbox": [
                192.0,
                96.0,
                9.0,
                17.0
            ],
            "segmentation": [
                [
                    192.0,
                    96.0,
                    201.0,
                    96.0,
                    201.0,
                    113.0,
                    192.0,
                    113.0
                ]
            ]
        }
    ],
    "lineColor": [
        0,
        255,
        0,
        128
    ],
    "fillColor": [
        255,
        0,
        0,
        128
    ],
    "imagePath": "F:\\2021\\3\u2014\u2014\u7b97\u6cd5\u7814\u7a76\\\u8f66\u8f86\u68c0\u6d4b\\1\u2014\u963f\u5e03\u624e\u6bd4\u8f66\u8f86\\labelme\\img\\GOOGLE_mosaic_clip_512_380.png",
    "imageData": "",
    "imageHeight": 512,
    "imageWidth": 512
}