{
    "version": "4.5.5",
    "flags": {},
    "shapes": [
        {
            "label": "car",
            "line_color": null,
            "fill_color": null,
            "points": [
                [
                    471.0,
                    466.0
                ],
                [
                    490.0,
                    466.0
                ],
                [
                    490.0,
                    477.0
                ],
                [
                    471.0,
                    477.0
                ]
            ],
            "shape_type": "polygon",
            "flags": {},
            "area": -1,
            "bbox": [
                471.0,
                466.0,
                19.0,
                11.0
            ],
            "segmentation": [
                [
                    471.0,
                    466.0,
                    490.0,
                    466.0,
                    490.0,
                    477.0,
                    471.0,
                    477.0
                ]
            ]
        },
        {
            "label": "track",
            "line_color": null,
            "fill_color": null,
            "points": [
                [
                    468.0,
                    354.0
                ],
                [
                    481.0,
                    354.0
                ],
                [
                    481.0,
                    391.0
                ],
                [
                    468.0,
                    391.0
                ]
            ],
            "shape_type": "polygon",
            "flags": {},
            "area": -1,
            "bbox": [
                468.0,
                354.0,
                13.0,
                37.0
            ],
            "segmentation": [
                [
                    468.0,
                    354.0,
                    481.0,
                    354.0,
                    481.0,
                    391.0,
                    468.0,
                    391.0
                ]
            ]
        },
        {
            "label": "car",
            "line_color": null,
            "fill_color": null,
            "points": [
                [
                    495.0,
                    384.0
                ],
                [
                    506.0,
                    384.0
                ],
                [
                    506.0,
                    407.0
                ],
                [
                    495.0,
                    407.0
                ]
            ],
            "shape_type": "polygon",
            "flags": {},
            "area": -1,
            "bbox": [
                495.0,
                384.0,
                11.0,
                23.0
            ],
            "segmentation": [
                [
                    495.0,
                    384.0,
                    506.0,
                    384.0,
                    506.0,
                    407.0,
                    495.0,
                    407.0
                ]
            ]
        },
        {
            "label": "car",
            "line_color": null,
            "fill_color": null,
            "points": [
                [
                    469.0,
                    465.0
                ],
                [
                    492.0,
                    465.0
                ],
                [
                    492.0,
                    478.0
                ],
                [
                    469.0,
                    478.0
                ]
            ],
            "shape_type": "polygon",
            "flags": {},
            "area": -1,
            "bbox": [
                469.0,
                465.0,
                23.0,
                13.0
            ],
            "segmentation": [
                [
                    469.0,
                    465.0,
                    492.0,
                    465.0,
                    492.0,
                    478.0,
                    469.0,
                    478.0
                ]
            ]
        },
        {
            "label": "track",
            "line_color": null,
            "fill_color": null,
            "points": [
                [
                    466.0,
                    353.0
                ],
                [
                    483.0,
                    353.0
                ],
                [
                    483.0,
                    394.0
                ],
                [
                    466.0,
                    394.0
                ]
            ],
            "shape_type": "polygon",
            "flags": {},
            "area": -1,
            "bbox": [
                466.0,
                353.0,
                17.0,
                41.0
            ],
            "segmentation": [
                [
                    466.0,
                    353.0,
                    483.0,
                    353.0,
                    483.0,
                    394.0,
                    466.0,
                    394.0
                ]
            ]
        }
    ],
    "lineColor": [
        0,
        255,
        0,
        128
    ],
    "fillColor": [
        255,
        0,
        0,
        128
    ],
    "imagePath": "F:\\2021\\3\u2014\u2014\u7b97\u6cd5\u7814\u7a76\\\u8f66\u8f86\u68c0\u6d4b\\1\u2014\u963f\u5e03\u624e\u6bd4\u8f66\u8f86\\labelme\\img\\GOOGLE_mosaic_clip_512_1382.png",
    "imageData": "",
    "imageHeight": 512,
    "imageWidth": 512
}